push_receiver/__init__.py
push_receiver/__main__.py
push_receiver/android_checkin_pb2.py
push_receiver/checkin_pb2.py
push_receiver/mcs_pb2.py
push_receiver/push_receiver.py
push_receiver-0.1.1.dist-info/METADATA
push_receiver-0.1.1.dist-info/WHEEL
push_receiver-0.1.1.dist-info/top_level.txt
push_receiver-0.1.1.dist-info/RECORD
