Metadata-Version: 2.1
Name: push-receiver
Version: 0.1.1
Summary: subscribe to GCM/FCM and receive notifications
Home-page: https://github.com/Francesco149/push_receiver
Author: Franc[e]sco
Author-email: lolisamurai@tfwno.gf
License: Unlicense
Keywords: fcm gcm push notification firebase google
Platform: UNKNOWN
Classifier: Programming Language :: Python :: 2
Classifier: Programming Language :: Python :: 3
Classifier: Intended Audience :: Developers
Classifier: License :: Public Domain
Classifier: Topic :: Software Development :: Libraries
Provides-Extra: listen
Provides-Extra: example
